quaeso/__init__.py
quaeso/__main__.py
quaeso/colorizer.py
quaeso/formatter.py
quaeso/reader.py
quaeso/writer.py
quaeso/yeet.py
quaeso-0.1.2.dist-info/LICENSE
quaeso-0.1.2.dist-info/METADATA
quaeso-0.1.2.dist-info/WHEEL
quaeso-0.1.2.dist-info/entry_points.txt
quaeso-0.1.2.dist-info/top_level.txt
quaeso-0.1.2.dist-info/RECORD
