Metadata-Version: 2.1
Name: quaeso
Version: 0.1.2
Summary: python cli program to send requests
Home-page: https://github.com/zahash/quaeso
Author: zahash
Author-email: zahash.z@gmail.com
License: MIT
Classifier: License :: OSI Approved :: MIT License
Classifier: Programming Language :: Python :: 3
Requires-Python: >=3.8
License-File: LICENSE
Requires-Dist: PyYAML ==6.*
Requires-Dist: Pygments ==2.*
Requires-Dist: lxml ==4.*
Requires-Dist: requests ==2.*
